{
  "title": "GFM#638 https://github.github.com/gfm/#example-638",
  "cases": [
    {
      "description": "Illegal attribute names",
      "input": "<a h*#ref=\"hi\">",
      "htmlAnswer": "<p>&lt;a h*#ref=&quot;hi&quot;&gt;</p>",
      "parseAnswer": {
        "type": "root",
        "meta": {},
        "children": [
          {
            "type": "paragraph",
            "children": [
              {
                "type": "text",
                "value": "<a h*#ref=\"hi\">",
                "position": {
                  "start": {
                    "line": 1,
                    "column": 1,
                    "offset": 0
                  },
                  "end": {
                    "line": 1,
                    "column": 16,
                    "offset": 15
                  }
                }
              }
            ],
            "position": {
              "start": {
                "line": 1,
                "column": 1,
                "offset": 0
              },
              "end": {
                "line": 1,
                "column": 16,
                "offset": 15
              }
            }
          }
        ],
        "position": {
          "start": {
            "line": 1,
            "column": 1,
            "offset": 0
          },
          "end": {
            "line": 1,
            "column": 16,
            "offset": 15
          }
        }
      }
    }
  ]
}