{
  "title": "GFM#486 https://github.github.com/gfm/#example-486",
  "cases": [
    {
      "description": "Rule 17",
      "input": "__<a href=\"__\">",
      "htmlAnswer": "<p>__<a href=\"__\"></p>",
      "parseAnswer": {
        "type": "root",
        "meta": {},
        "children": [
          {
            "type": "paragraph",
            "children": [
              {
                "type": "text",
                "value": "__",
                "position": {
                  "start": {
                    "line": 1,
                    "column": 1,
                    "offset": 0
                  },
                  "end": {
                    "line": 1,
                    "column": 3,
                    "offset": 2
                  }
                }
              },
              {
                "type": "htmlInline",
                "value": "<a href=\"__\">",
                "htmlType": "open",
                "tagName": "a",
                "attributes": [
                  {
                    "name": "href",
                    "value": "__"
                  }
                ],
                "selfClosed": false,
                "position": {
                  "start": {
                    "line": 1,
                    "column": 3,
                    "offset": 2
                  },
                  "end": {
                    "line": 1,
                    "column": 16,
                    "offset": 15
                  }
                }
              }
            ],
            "position": {
              "start": {
                "line": 1,
                "column": 1,
                "offset": 0
              },
              "end": {
                "line": 1,
                "column": 16,
                "offset": 15
              }
            }
          }
        ],
        "position": {
          "start": {
            "line": 1,
            "column": 1,
            "offset": 0
          },
          "end": {
            "line": 1,
            "column": 16,
            "offset": 15
          }
        }
      }
    }
  ]
}